dtool_lookup_server_plugin_scaffolding/__init__.py
dtool_lookup_server_plugin_scaffolding/config.py
dtool_lookup_server_plugin_scaffolding/utils.py
dtool_lookup_server_plugin_scaffolding-0.1.4.dist-info/LICENSE
dtool_lookup_server_plugin_scaffolding-0.1.4.dist-info/METADATA
dtool_lookup_server_plugin_scaffolding-0.1.4.dist-info/WHEEL
dtool_lookup_server_plugin_scaffolding-0.1.4.dist-info/entry_points.txt
dtool_lookup_server_plugin_scaffolding-0.1.4.dist-info/top_level.txt
dtool_lookup_server_plugin_scaffolding-0.1.4.dist-info/RECORD
