Metadata-Version: 2.1
Name: dtool-lookup-server-plugin-scaffolding
Version: 0.1.4
Summary: This scaffolding serves as a minimal template for dtool lookup server plugin developments.
Home-page: https://github.com/IMTEK-Simulation/dtool-lookup-server-plugin-scaffolding
Author: Johannes Hörmann
Author-email: johannes.hoermann@imtek.uni-freiburg.de
License: MIT
Download-URL: https://github.com/IMTEK-Simulation/dtool-lookup-server-plugin-scaffolding/tarball/0.1.4
Platform: UNKNOWN
Requires-Dist: dtool-lookup-server (>=0.17.2)
